{
  "project_info": {
    "project_number": "516369218141",
    "project_id": "nid-de-poulet",
    "storage_bucket": "nid-de-poulet.firebasestorage.app"
  },
  "client": [
    {
      "client_info": {
        "mobilesdk_app_id": "1:516369218141:android:0e3b3feadf7e4e597c6bb4",
        "android_client_info": {
          "package_name": "com.android.niddepoulet"
        }
      },
      "oauth_client": [],
      "api_key": [
        {
          "current_key": "AIzaSyBMheVQeYoVfV_QfyF85FTOOwNijtiHmnM"
        }
      ],
      "services": {
        "appinvite_service": {
          "other_platform_oauth_client": []
        }
      }
    }
  ],
  "configuration_version": "1"
}